colorog/__init__.py
colorog-1.0.2.dist-info/licenses/LICENSE
colorog-1.0.2.dist-info/METADATA
colorog-1.0.2.dist-info/WHEEL
colorog-1.0.2.dist-info/top_level.txt
colorog-1.0.2.dist-info/RECORD
