Metadata-Version: 2.4
Name: colorog
Version: 1.0.2
Summary: Make Python output not boring!
Home-page: https://github.com/tughw/colorog
Author: Alex Holland
Author-email: <alexh9392@hotmail.com>
License: MIT License
Keywords: colorog
Classifier: Environment :: Console
Classifier: Programming Language :: Python :: 3.9
Classifier: Programming Language :: Python :: 3.10
Classifier: Programming Language :: Python :: 3.11
Classifier: Programming Language :: Python :: 3.12
Classifier: Programming Language :: Python :: 3.13
Classifier: Programming Language :: Python :: 3.14
Classifier: Programming Language :: Python :: 3.15
Classifier: Development Status :: 6 - Mature
Classifier: Operating System :: OS Independent
License-File: LICENSE
Requires-Dist: termcolor
Requires-Dist: colorama
Requires-Dist: affixr
Dynamic: author
Dynamic: author-email
Dynamic: classifier
Dynamic: description
Dynamic: description-content-type
Dynamic: home-page
Dynamic: keywords
Dynamic: license
Dynamic: license-file
Dynamic: requires-dist
Dynamic: summary
